paybybot2/__init__.py
paybybot2/__main__.py
paybybot2/bot.py
paybybot2/config.py
paybybot2/notifs.py
paybybot2-0.0.2.dist-info/LICENSE
paybybot2-0.0.2.dist-info/METADATA
paybybot2-0.0.2.dist-info/WHEEL
paybybot2-0.0.2.dist-info/entry_points.txt
paybybot2-0.0.2.dist-info/top_level.txt
paybybot2-0.0.2.dist-info/RECORD
