Metadata-Version: 2.1
Name: paybybot2
Version: 0.0.2
Summary: CLI interface to https://www.paybyphone.fr/
Home-page: https://github.com/louisabraham/paybybot2
Author: Louis Abraham
Author-email: louis.abraham@yahoo.fr
License: MIT
Platform: UNKNOWN
Classifier: Topic :: Utilities
Classifier: Topic :: Security :: Cryptography
Requires-Python: >=3.6
License-File: LICENSE
Requires-Dist: pyyaml
Requires-Dist: requests
Requires-Dist: click
